{
    "exists": true,
    "title": "Castle Bottom to Yateley and Hawley Commons",
    "url": "https://en.wikipedia.org/wiki/Castle_Bottom_to_Yateley_and_Hawley_Commons",
    "summary": "Castle Bottom to Yateley and Hawley Commons is a 922.7-hectare (2,280-acre) biological Site of Special Scientific Interest north of Fleet in Hampshire. It is part of Thames Basin Heaths Special Protection Area for the conservation of wild birds and an area of 30.8 hectares (76 acres) is designated a national nature reserve called Castle Bottom.\nThis site of heathland and conifer plantation has an internationally important population of Dartford warbler and populations of two other protected birds, woodlark and nightjar. It also has an outstanding assemblage of dragonflies and damselflies, with 19 out of the 37 British species. Other invertebrates include the nationally rare conopid fly, Myopa fasciata.\n\n\n== References ==",
    "text": "Castle Bottom to Yateley and Hawley Commons is a 922.7-hectare (2,280-acre) biological Site of Special Scientific Interest north of Fleet in Hampshire. It is part of Thames Basin Heaths Special Protection Area for the conservation of wild birds and an area of 30.8 hectares (76 acres) is designated a national nature reserve called Castle Bottom.\nThis site of heathland and conifer plantation has an internationally important population of Dartford warbler and populations of two other protected birds, woodlark and nightjar. It also has an outstanding assemblage of dragonflies and damselflies, with 19 out of the 37 British species. Other invertebrates include the nationally rare conopid fly, Myopa fasciata."
}