{
    "exists": true,
    "title": "School of the Nations",
    "url": "https://en.wikipedia.org/wiki/School_of_the_Nations",
    "summary": "School of the Nations may refer to:\n\nSchool of the Nations (Guyana)\nSchool of the Nations (Macau) (Portuguese name: Escola das Nações)\nSchool of the Nations (Bahá'í – Brazil) (Portuguese name: Escola das Nações)",
    "text": "School of the Nations may refer to:\n\nSchool of the Nations (Guyana)\nSchool of the Nations (Macau) (Portuguese name: Escola das Nações)\nSchool of the Nations (Bahá'í – Brazil) (Portuguese name: Escola das Nações)"
}