{
    "exists": true,
    "title": "The Square Ring",
    "url": "https://en.wikipedia.org/wiki/The_Square_Ring",
    "summary": "The Square Ring may refer to:\n\nThe Square Ring (play) a 1952 play by Ralph Peterson\nThe Square Ring (1953 film), a British tragi-comic drama film, based on the play\nThe Square Ring (1960 film), an Australian TV play\nThe Square Ring (Play of the Week), a 1959 British TV play for Play of the Week\nBoxing ring, the space in which a boxing match occurs",
    "text": "The Square Ring may refer to:\n\nThe Square Ring (play) a 1952 play by Ralph Peterson\nThe Square Ring (1953 film), a British tragi-comic drama film, based on the play\nThe Square Ring (1960 film), an Australian TV play\nThe Square Ring (Play of the Week), a 1959 British TV play for Play of the Week\nBoxing ring, the space in which a boxing match occurs"
}